vt_cdk_vpc_construct/__init__.py
vt_cdk_vpc_construct/py.typed
vt_cdk_vpc_construct/_jsii/__init__.py
vt_cdk_vpc_construct/_jsii/vt-vpc-construct@0.0.9.jsii.tgz
vt.cdk_vpc_constuct-0.0.9.dist-info/LICENSE
vt.cdk_vpc_constuct-0.0.9.dist-info/METADATA
vt.cdk_vpc_constuct-0.0.9.dist-info/WHEEL
vt.cdk_vpc_constuct-0.0.9.dist-info/top_level.txt
vt.cdk_vpc_constuct-0.0.9.dist-info/RECORD
