Metadata-Version: 2.1
Name: vt.cdk-vpc-constuct
Version: 0.0.9
Summary: Deploys VPC with tags and small EC2 NATGateways to reduce and track cost of development environments
Home-page: https://github.com/vaughngit/projen-awsvpc-constuct.git
Author: VaughnTech<alvin.vaughn@outlook.com>
License: Apache-2.0
Project-URL: Source, https://github.com/vaughngit/projen-awsvpc-constuct.git
Platform: UNKNOWN
Classifier: Intended Audience :: Developers
Classifier: Operating System :: OS Independent
Classifier: Programming Language :: JavaScript
Classifier: Programming Language :: Python :: 3 :: Only
Classifier: Programming Language :: Python :: 3.7
Classifier: Programming Language :: Python :: 3.8
Classifier: Programming Language :: Python :: 3.9
Classifier: Programming Language :: Python :: 3.10
Classifier: Typing :: Typed
Classifier: Development Status :: 5 - Production/Stable
Classifier: License :: OSI Approved
Requires-Python: ~=3.7
License-File: LICENSE
Requires-Dist: aws-cdk-lib (<3.0.0,>=2.60.0)
Requires-Dist: constructs (<11.0.0,>=10.0.5)
Requires-Dist: jsii (<2.0.0,>=1.73.0)
Requires-Dist: publication (>=0.0.3)
Requires-Dist: typeguard (~=2.13.3)
